{
  "users": [
    {
      "mail": "",
      "des": "",
      "author": "",
      "id": 252331504042
    },
    {
      "mail": "",
      "des": "",
      "author": "",
      "id": 356908558092
    },
    {
      "id": 1078662136284,
      "mail": "",
      "des": "",
      "author": ""
    },
    {
      "id": 1087414079308,
      "mail": "",
      "des": "",
      "author": ""
    },
    {
      "id": 552173011553,
      "mail": "",
      "des": "",
      "author": ""
    },
    {
      "id": 327884408275,
      "mail": "",
      "des": "",
      "author": ""
    },
    {
      "id": 1581693418182,
      "mail": "",
      "des": "",
      "author": ""
    },
    {
      "id": 722698321364,
      "mail": "",
      "des": "",
      "author": ""
    }
  ]
}